{
"classname": null,
"name": null,
"animation": {
"classname": null,
"name": "AnimationManager",
"actionlist": []
},
"dataScale": 1,
"designHeight": 50,
"designWidth": 1140,
"textures": [],
"texturesPng": [
"imgres/main/b_bk.png",
"imgres/main/icon_bk.png",
"imgres/common/contribute.png",
"imgres/common/corpsmoney.png",
"imgres/main/fight_bk.png",
"imgres/corps/corpsPower.png",
"imgres/common/yuanbao.png",
"imgres/common/silver.png"
],
"version": "1.5.0.0",
"widgetTree": {
"classname": "Panel",
"name": null,
"children": [
{
"classname": "Panel",
"name": null,
"children": [
{
"classname": "ImageView",
"name": null,
"children": [
{
"classname": "ImageView",
"name": null,
"children": [],
"options": {
"__type": "ImageViewSurrogate:#EditorCommon.JsonModel.Component.GUI",
"classname": "ImageView",
"name": "Image_8",
"ZOrder": 0,
"actiontag": 9649161,
"anchorPointX": 0.5,
"anchorPointY": 0.5,
"classType": "CocoStudio.EngineAdapterWrap.CSImageView",
"colorB": 255,
"colorG": 255,
"colorR": 255,
"customProperty": "",
"flipX": false,
"flipY": false,
"height": 55,
"ignoreSize": true,
"layoutParameter": null,
"opacity": 255,
"positionPercentX": -0.412162155,
"positionPercentY": -0.0222222228,
"positionType": 0,
"rotation": 0,
"scaleX": 1,
"scaleY": 1,
"sizePercentX": 0.364864856,
"sizePercentY": 1.22222221,
"sizeType": 0,
"tag": 117,
"touchAble": false,
"useMergedTexture": false,
"visible": true,
"width": 54,
"x": -61,
"y": -1,
"capInsetsHeight": 1,
"capInsetsWidth": 1,
"capInsetsX": 0,
"capInsetsY": 0,
"fileName": null,
"fileNameData": {
"path": "imgres/main/icon_bk.png",
"plistFile": "",
"resourceType": 0
},
"scale9Enable": false,
"scale9Height": 55,
"scale9Width": 54
}
},
{
"classname": "ImageView",
"name": null,
"children": [],
"options": {
"__type": "ImageViewSurrogate:#EditorCommon.JsonModel.Component.GUI",
"classname": "ImageView",
"name": "Image_contibute",
"ZOrder": 0,
"actiontag": 44307383,
"anchorPointX": 0.5,
"anchorPointY": 0.5,
"classType": "CocoStudio.EngineAdapterWrap.CSImageView",
"colorB": 255,
"colorG": 255,
"colorR": 255,
"customProperty": "",
"flipX": false,
"flipY": false,
"height": 110,
"ignoreSize": true,
"layoutParameter": null,
"opacity": 255,
"positionPercentX": -0.4054054,
"positionPercentY": -0.0222222228,
"positionType": 0,
"rotation": 0,
"scaleX": 0.4999999,
"scaleY": 0.4999999,
"sizePercentX": 0.7432432,
"sizePercentY": 2.44444442,
"sizeType": 0,
"tag": 120,
"touchAble": false,
"useMergedTexture": false,
"visible": true,
"width": 110,
"x": -60,
"y": -1,
"capInsetsHeight": 1,
"capInsetsWidth": 1,
"capInsetsX": 0,
"capInsetsY": 0,
"fileName": null,
"fileNameData": {
"path": "imgres/common/contribute.png",
"plistFile": "",
"resourceType": 0
},
"scale9Enable": false,
"scale9Height": 110,
"scale9Width": 110
}
},
{
"classname": "Label",
"name": null,
"children": [],
"options": {
"__type": "LabelSurrogate:#EditorCommon.JsonModel.Component.GUI",
"classname": "Label",
"name": "Label_cNum",
"ZOrder": 0,
"actiontag": 44794021,
"anchorPointX": 0.5,
"anchorPointY": 0.5,
"classType": "CocoStudio.EngineAdapterWrap.CSLabel",
"colorB": 255,
"colorG": 255,
"colorR": 255,
"customProperty": "",
"flipX": false,
"flipY": false,
"height": 30,
"ignoreSize": false,
"layoutParameter": null,
"opacity": 255,
"positionPercentX": 0.101351351,
"positionPercentY": -0.0222222228,
"positionType": 0,
"rotation": 0,
"scaleX": 1,
"scaleY": 1,
"sizePercentX": 0.6756757,
"sizePercentY": 0.6666667,
"sizeType": 0,
"tag": 122,
"touchAble": false,
"useMergedTexture": false,
"visible": true,
"width": 100,
"x": 15,
"y": -1,
"areaHeight": 30,
"areaWidth": 100,
"fontFile": null,
"fontName": "微软雅黑",
"fontSize": 23,
"hAlignment": 0,
"text": "",
"touchScaleEnable": false,
"vAlignment": 1
}
}
],
"options": {
"__type": "ImageViewSurrogate:#EditorCommon.JsonModel.Component.GUI",
"classname": "ImageView",
"name": "Image_4",
"ZOrder": 0,
"actiontag": 3409123,
"anchorPointX": 0.5,
"anchorPointY": 0.5,
"classType": "CocoStudio.EngineAdapterWrap.CSImageView",
"colorB": 255,
"colorG": 255,
"colorR": 255,
"customProperty": "",
"flipX": false,
"flipY": false,
"height": 45,
"ignoreSize": true,
"layoutParameter": null,
"opacity": 255,
"positionPercentX": 0.44625,
"positionPercentY": 0.44,
"positionType": 0,
"rotation": 0,
"scaleX": 1,
"scaleY": 1,
"sizePercentX": 0.1875,
"sizePercentY": 0.6,
"sizeType": 0,
"tag": 113,
"touchAble": false,
"useMergedTexture": false,
"visible": true,
"width": 148,
"x": 357,
"y": 22,
"capInsetsHeight": 1,
"capInsetsWidth": 1,
"capInsetsX": 0,
"capInsetsY": 0,
"fileName": null,
"fileNameData": {
"path": "imgres/main/b_bk.png",
"plistFile": "",
"resourceType": 0
},
"scale9Enable": false,
"scale9Height": 45,
"scale9Width": 148
}
},
{
"classname": "ImageView",
"name": null,
"children": [
{
"classname": "ImageView",
"name": null,
"children": [],
"options": {
"__type": "ImageViewSurrogate:#EditorCommon.JsonModel.Component.GUI",
"classname": "ImageView",
"name": "Image_8",
"ZOrder": 0,
"actiontag": 31709526,
"anchorPointX": 0.5,
"anchorPointY": 0.5,
"classType": "CocoStudio.EngineAdapterWrap.CSImageView",
"colorB": 255,
"colorG": 255,
"colorR": 255,
"customProperty": "",
"flipX": false,
"flipY": false,
"height": 55,
"ignoreSize": true,
"layoutParameter": null,
"opacity": 255,
"positionPercentX": -0.412162155,
"positionPercentY": -0.0222222228,
"positionType": 0,
"rotation": 0,
"scaleX": 1,
"scaleY": 1,
"sizePercentX": 0.364864856,
"sizePercentY": 1.22222221,
"sizeType": 0,
"tag": 130,
"touchAble": false,
"useMergedTexture": false,
"visible": true,
"width": 54,
"x": -61,
"y": -1,
"capInsetsHeight": 1,
"capInsetsWidth": 1,
"capInsetsX": 0,
"capInsetsY": 0,
"fileName": null,
"fileNameData": {
"path": "imgres/main/icon_bk.png",
"plistFile": "",
"resourceType": 0
},
"scale9Enable": false,
"scale9Height": 55,
"scale9Width": 54
}
},
{
"classname": "ImageView",
"name": null,
"children": [],
"options": {
"__type": "ImageViewSurrogate:#EditorCommon.JsonModel.Component.GUI",
"classname": "ImageView",
"name": "Image_money",
"ZOrder": 0,
"actiontag": 16950286,
"anchorPointX": 0.5,
"anchorPointY": 0.5,
"classType": "CocoStudio.EngineAdapterWrap.CSImageView",
"colorB": 255,
"colorG": 255,
"colorR": 255,
"customProperty": "",
"flipX": false,
"flipY": false,
"height": 110,
"ignoreSize": true,
"layoutParameter": null,
"opacity": 255,
"positionPercentX": -0.4054054,
"positionPercentY": -0.0222222228,
"positionType": 0,
"rotation": 0,
"scaleX": 0.4999999,
"scaleY": 0.4999999,
"sizePercentX": 0.7432432,
"sizePercentY": 2.44444442,
"sizeType": 0,
"tag": 131,
"touchAble": false,
"useMergedTexture": false,
"visible": true,
"width": 110,
"x": -60,
"y": -1,
"capInsetsHeight": 1,
"capInsetsWidth": 1,
"capInsetsX": 0,
"capInsetsY": 0,
"fileName": null,
"fileNameData": {
"path": "imgres/common/corpsmoney.png",
"plistFile": "",
"resourceType": 0
},
"scale9Enable": false,
"scale9Height": 110,
"scale9Width": 110
}
},
{
"classname": "Label",
"name": null,
"children": [],
"options": {
"__type": "LabelSurrogate:#EditorCommon.JsonModel.Component.GUI",
"classname": "Label",
"name": "Label_MNum",
"ZOrder": 0,
"actiontag": 18334850,
"anchorPointX": 0.5,
"anchorPointY": 0.5,
"classType": "CocoStudio.EngineAdapterWrap.CSLabel",
"colorB": 255,
"colorG": 255,
"colorR": 255,
"customProperty": "",
"flipX": false,
"flipY": false,
"height": 30,
"ignoreSize": false,
"layoutParameter": null,
"opacity": 255,
"positionPercentX": 0.101351351,
"positionPercentY": -0.0222222228,
"positionType": 0,
"rotation": 0,
"scaleX": 1,
"scaleY": 1,
"sizePercentX": 0.6756757,
"sizePercentY": 0.6666667,
"sizeType": 0,
"tag": 132,
"touchAble": false,
"useMergedTexture": false,
"visible": true,
"width": 100,
"x": 15,
"y": -1,
"areaHeight": 30,
"areaWidth": 100,
"fontFile": null,
"fontName": "微软雅黑",
"fontSize": 23,
"hAlignment": 0,
"text": "",
"touchScaleEnable": false,
"vAlignment": 1
}
}
],
"options": {
"__type": "ImageViewSurrogate:#EditorCommon.JsonModel.Component.GUI",
"classname": "ImageView",
"name": "Image_4_0",
"ZOrder": 0,
"actiontag": 63863600,
"anchorPointX": 0.5,
"anchorPointY": 0.5,
"classType": "CocoStudio.EngineAdapterWrap.CSImageView",
"colorB": 255,
"colorG": 255,
"colorR": 255,
"customProperty": "",
"flipX": false,
"flipY": false,
"height": 45,
"ignoreSize": true,
"layoutParameter": null,
"opacity": 255,
"positionPercentX": 0.63625,
"positionPercentY": 0.44,
"positionType": 0,
"rotation": 0,
"scaleX": 1,
"scaleY": 1,
"sizePercentX": 0.1875,
"sizePercentY": 0.6,
"sizeType": 0,
"tag": 129,
"touchAble": false,
"useMergedTexture": false,
"visible": true,
"width": 148,
"x": 509,
"y": 22,
"capInsetsHeight": 1,
"capInsetsWidth": 1,
"capInsetsX": 0,
"capInsetsY": 0,
"fileName": null,
"fileNameData": {
"path": "imgres/main/b_bk.png",
"plistFile": "",
"resourceType": 0
},
"scale9Enable": false,
"scale9Height": 45,
"scale9Width": 148
}
},
{
"classname": "ImageView",
"name": null,
"children": [
{
"classname": "ImageView",
"name": null,
"children": [],
"options": {
"__type": "ImageViewSurrogate:#EditorCommon.JsonModel.Component.GUI",
"classname": "ImageView",
"name": "Image_80",
"ZOrder": 0,
"actiontag": 59616770,
"anchorPointX": 0.5,
"anchorPointY": 0.5,
"classType": "CocoStudio.EngineAdapterWrap.CSImageView",
"colorB": 255,
"colorG": 255,
"colorR": 255,
"customProperty": "",
"flipX": false,
"flipY": false,
"height": 24,
"ignoreSize": true,
"layoutParameter": null,
"opacity": 255,
"positionPercentX": -0.26,
"positionPercentY": -0.0227272734,
"positionType": 0,
"rotation": 0,
"scaleX": 1,
"scaleY": 1,
"sizePercentX": 0.46,
"sizePercentY": 0.545454562,
"sizeType": 0,
"tag": 134,
"touchAble": false,
"useMergedTexture": false,
"visible": true,
"width": 92,
"x": -52,
"y": -1,
"capInsetsHeight": 1,
"capInsetsWidth": 1,
"capInsetsX": 0,
"capInsetsY": 0,
"fileName": null,
"fileNameData": {
"path": "imgres/corps/corpsPower.png",
"plistFile": "",
"resourceType": 0
},
"scale9Enable": false,
"scale9Height": 24,
"scale9Width": 92
}
},
{
"classname": "Label",
"name": null,
"children": [],
"options": {
"__type": "LabelSurrogate:#EditorCommon.JsonModel.Component.GUI",
"classname": "Label",
"name": "Label_power",
"ZOrder": 0,
"actiontag": 64229099,
"anchorPointX": 0.5,
"anchorPointY": 0.5,
"classType": "CocoStudio.EngineAdapterWrap.CSLabel",
"colorB": 255,
"colorG": 255,
"colorR": 255,
"customProperty": "",
"flipX": false,
"flipY": false,
"height": 30,
"ignoreSize": false,
"layoutParameter": null,
"opacity": 255,
"positionPercentX": 0.29,
"positionPercentY": -0.0227272734,
"positionType": 0,
"rotation": 0,
"scaleX": 1,
"scaleY": 1,
"sizePercentX": 0.6,
"sizePercentY": 0.6818182,
"sizeType": 0,
"tag": 136,
"touchAble": false,
"useMergedTexture": false,
"visible": true,
"width": 120,
"x": 58,
"y": -1,
"areaHeight": 30,
"areaWidth": 120,
"fontFile": null,
"fontName": "微软雅黑",
"fontSize": 23,
"hAlignment": 0,
"text": "",
"touchScaleEnable": false,
"vAlignment": 1
}
}
],
"options": {
"__type": "ImageViewSurrogate:#EditorCommon.JsonModel.Component.GUI",
"classname": "ImageView",
"name": "Image_4_1",
"ZOrder": 0,
"actiontag": 58819868,
"anchorPointX": 0.5,
"anchorPointY": 0.5,
"classType": "CocoStudio.EngineAdapterWrap.CSImageView",
"colorB": 255,
"colorG": 255,
"colorR": 255,
"customProperty": "",
"flipX": false,
"flipY": false,
"height": 44,
"ignoreSize": false,
"layoutParameter": null,
"opacity": 255,
"positionPercentX": 0.845,
"positionPercentY": 0.44,
"positionType": 0,
"rotation": 0,
"scaleX": 1,
"scaleY": 1,
"sizePercentX": 0.25,
"sizePercentY": 0.88,
"sizeType": 0,
"tag": 133,
"touchAble": false,
"useMergedTexture": false,
"visible": true,
"width": 200,
"x": 676,
"y": 22,
"capInsetsHeight": 1,
"capInsetsWidth": 1,
"capInsetsX": 0,
"capInsetsY": 0,
"fileName": null,
"fileNameData": {
"path": "imgres/main/fight_bk.png",
"plistFile": "",
"resourceType": 0
},
"scale9Enable": false,
"scale9Height": 44,
"scale9Width": 200
}
},
{
"classname": "ImageView",
"name": null,
"children": [
{
"classname": "ImageView",
"name": null,
"children": [],
"options": {
"__type": "ImageViewSurrogate:#EditorCommon.JsonModel.Component.GUI",
"classname": "ImageView",
"name": "Image_8",
"ZOrder": 0,
"actiontag": 61885537,
"anchorPointX": 0.5,
"anchorPointY": 0.5,
"classType": "CocoStudio.EngineAdapterWrap.CSImageView",
"colorB": 255,
"colorG": 255,
"colorR": 255,
"customProperty": "",
"flipX": false,
"flipY": false,
"height": 55,
"ignoreSize": true,
"layoutParameter": null,
"opacity": 255,
"positionPercentX": -0.406666666,
"positionPercentY": -0.0333333351,
"positionType": 0,
"rotation": 0,
"scaleX": 1,
"scaleY": 1,
"sizePercentX": 0.36,
"sizePercentY": 1.83333337,
"sizeType": 0,
"tag": 151,
"touchAble": false,
"useMergedTexture": false,
"visible": true,
"width": 54,
"x": -61,
"y": -1,
"capInsetsHeight": 1,
"capInsetsWidth": 1,
"capInsetsX": 0,
"capInsetsY": 0,
"fileName": null,
"fileNameData": {
"path": "imgres/main/icon_bk.png",
"plistFile": "",
"resourceType": 0
},
"scale9Enable": false,
"scale9Height": 55,
"scale9Width": 54
}
},
{
"classname": "ImageView",
"name": null,
"children": [],
"options": {
"__type": "ImageViewSurrogate:#EditorCommon.JsonModel.Component.GUI",
"classname": "ImageView",
"name": "Image_contibute",
"ZOrder": 0,
"actiontag": 20098922,
"anchorPointX": 0.5,
"anchorPointY": 0.5,
"classType": "CocoStudio.EngineAdapterWrap.CSImageView",
"colorB": 255,
"colorG": 255,
"colorR": 255,
"customProperty": "",
"flipX": false,
"flipY": false,
"height": 100,
"ignoreSize": true,
"layoutParameter": null,
"opacity": 255,
"positionPercentX": -0.4,
"positionPercentY": -0.0333333351,
"positionType": 0,
"rotation": 0,
"scaleX": 0.4999999,
"scaleY": 0.4999999,
"sizePercentX": 0.6666667,
"sizePercentY": 3.33333325,
"sizeType": 0,
"tag": 152,
"touchAble": false,
"useMergedTexture": false,
"visible": true,
"width": 100,
"x": -60,
"y": -1,
"capInsetsHeight": 1,
"capInsetsWidth": 1,
"capInsetsX": 0,
"capInsetsY": 0,
"fileName": null,
"fileNameData": {
"path": "imgres/common/yuanbao.png",
"plistFile": "",
"resourceType": 0
},
"scale9Enable": false,
"scale9Height": 100,
"scale9Width": 100
}
},
{
"classname": "Label",
"name": null,
"children": [],
"options": {
"__type": "LabelSurrogate:#EditorCommon.JsonModel.Component.GUI",
"classname": "Label",
"name": "Label_SNum",
"ZOrder": 0,
"actiontag": 46672571,
"anchorPointX": 0.5,
"anchorPointY": 0.5,
"classType": "CocoStudio.EngineAdapterWrap.CSLabel",
"colorB": 255,
"colorG": 255,
"colorR": 255,
"customProperty": "",
"flipX": false,
"flipY": false,
"height": 30,
"ignoreSize": false,
"layoutParameter": null,
"opacity": 255,
"positionPercentX": 0.1,
"positionPercentY": -0.0333333351,
"positionType": 0,
"rotation": 0,
"scaleX": 1,
"scaleY": 1,
"sizePercentX": 0.6666667,
"sizePercentY": 1,
"sizeType": 0,
"tag": 153,
"touchAble": false,
"useMergedTexture": false,
"visible": true,
"width": 100,
"x": 15,
"y": -1,
"areaHeight": 30,
"areaWidth": 100,
"fontFile": null,
"fontName": "微软雅黑",
"fontSize": 23,
"hAlignment": 0,
"text": "",
"touchScaleEnable": false,
"vAlignment": 1
}
}
],
"options": {
"__type": "ImageViewSurrogate:#EditorCommon.JsonModel.Component.GUI",
"classname": "ImageView",
"name": "Image_4_2",
"ZOrder": 0,
"actiontag": 42202829,
"anchorPointX": 0.5,
"anchorPointY": 0.5,
"classType": "CocoStudio.EngineAdapterWrap.CSImageView",
"colorB": 255,
"colorG": 255,
"colorR": 255,
"customProperty": "",
"flipX": false,
"flipY": false,
"height": 30,
"ignoreSize": false,
"layoutParameter": null,
"opacity": 255,
"positionPercentX": 0.0625,
"positionPercentY": 0.44,
"positionType": 0,
"rotation": 0,
"scaleX": 1,
"scaleY": 1,
"sizePercentX": 0.1875,
"sizePercentY": 0.6,
"sizeType": 0,
"tag": 150,
"touchAble": false,
"useMergedTexture": false,
"visible": true,
"width": 150,
"x": 50,
"y": 22,
"capInsetsHeight": 1,
"capInsetsWidth": 1,
"capInsetsX": 0,
"capInsetsY": 0,
"fileName": null,
"fileNameData": {
"path": "imgres/main/b_bk.png",
"plistFile": "",
"resourceType": 0
},
"scale9Enable": false,
"scale9Height": 30,
"scale9Width": 150
}
},
{
"classname": "ImageView",
"name": null,
"children": [
{
"classname": "ImageView",
"name": null,
"children": [],
"options": {
"__type": "ImageViewSurrogate:#EditorCommon.JsonModel.Component.GUI",
"classname": "ImageView",
"name": "Image_8",
"ZOrder": 0,
"actiontag": 50671322,
"anchorPointX": 0.5,
"anchorPointY": 0.5,
"classType": "CocoStudio.EngineAdapterWrap.CSImageView",
"colorB": 255,
"colorG": 255,
"colorR": 255,
"customProperty": "",
"flipX": false,
"flipY": false,
"height": 55,
"ignoreSize": true,
"layoutParameter": null,
"opacity": 255,
"positionPercentX": -0.406666666,
"positionPercentY": -0.0333333351,
"positionType": 0,
"rotation": 0,
"scaleX": 1,
"scaleY": 1,
"sizePercentX": 0.36,
"sizePercentY": 1.83333337,
"sizeType": 0,
"tag": 155,
"touchAble": false,
"useMergedTexture": false,
"visible": true,
"width": 54,
"x": -61,
"y": -1,
"capInsetsHeight": 1,
"capInsetsWidth": 1,
"capInsetsX": 0,
"capInsetsY": 0,
"fileName": null,
"fileNameData": {
"path": "imgres/main/icon_bk.png",
"plistFile": "",
"resourceType": 0
},
"scale9Enable": false,
"scale9Height": 55,
"scale9Width": 54
}
},
{
"classname": "ImageView",
"name": null,
"children": [],
"options": {
"__type": "ImageViewSurrogate:#EditorCommon.JsonModel.Component.GUI",
"classname": "ImageView",
"name": "Image_contibute",
"ZOrder": 0,
"actiontag": 53388721,
"anchorPointX": 0.5,
"anchorPointY": 0.5,
"classType": "CocoStudio.EngineAdapterWrap.CSImageView",
"colorB": 255,
"colorG": 255,
"colorR": 255,
"customProperty": "",
"flipX": false,
"flipY": false,
"height": 100,
"ignoreSize": true,
"layoutParameter": null,
"opacity": 255,
"positionPercentX": -0.4,
"positionPercentY": -0.0333333351,
"positionType": 0,
"rotation": 0,
"scaleX": 0.4999999,
"scaleY": 0.4999999,
"sizePercentX": 0.6666667,
"sizePercentY": 3.33333325,
"sizeType": 0,
"tag": 156,
"touchAble": false,
"useMergedTexture": false,
"visible": true,
"width": 100,
"x": -60,
"y": -1,
"capInsetsHeight": 1,
"capInsetsWidth": 1,
"capInsetsX": 0,
"capInsetsY": 0,
"fileName": null,
"fileNameData": {
"path": "imgres/common/silver.png",
"plistFile": "",
"resourceType": 0
},
"scale9Enable": false,
"scale9Height": 100,
"scale9Width": 100
}
},
{
"classname": "Label",
"name": null,
"children": [],
"options": {
"__type": "LabelSurrogate:#EditorCommon.JsonModel.Component.GUI",
"classname": "Label",
"name": "Label_gNum",
"ZOrder": 0,
"actiontag": 10736447,
"anchorPointX": 0.5,
"anchorPointY": 0.5,
"classType": "CocoStudio.EngineAdapterWrap.CSLabel",
"colorB": 255,
"colorG": 255,
"colorR": 255,
"customProperty": "",
"flipX": false,
"flipY": false,
"height": 30,
"ignoreSize": false,
"layoutParameter": null,
"opacity": 255,
"positionPercentX": 0.1,
"positionPercentY": -0.0333333351,
"positionType": 0,
"rotation": 0,
"scaleX": 1,
"scaleY": 1,
"sizePercentX": 0.6666667,
"sizePercentY": 1,
"sizeType": 0,
"tag": 157,
"touchAble": false,
"useMergedTexture": false,
"visible": true,
"width": 100,
"x": 15,
"y": -1,
"areaHeight": 30,
"areaWidth": 100,
"fontFile": null,
"fontName": "微软雅黑",
"fontSize": 23,
"hAlignment": 0,
"text": "",
"touchScaleEnable": false,
"vAlignment": 1
}
}
],
"options": {
"__type": "ImageViewSurrogate:#EditorCommon.JsonModel.Component.GUI",
"classname": "ImageView",
"name": "Image_4_3",
"ZOrder": 0,
"actiontag": 42426319,
"anchorPointX": 0.5,
"anchorPointY": 0.5,
"classType": "CocoStudio.EngineAdapterWrap.CSImageView",
"colorB": 255,
"colorG": 255,
"colorR": 255,
"customProperty": "",
"flipX": false,
"flipY": false,
"height": 30,
"ignoreSize": false,
"layoutParameter": null,
"opacity": 255,
"positionPercentX": 0.255,
"positionPercentY": 0.44,
"positionType": 0,
"rotation": 0,
"scaleX": 1,
"scaleY": 1,
"sizePercentX": 0.1875,
"sizePercentY": 0.6,
"sizeType": 0,
"tag": 154,
"touchAble": false,
"useMergedTexture": false,
"visible": true,
"width": 150,
"x": 204,
"y": 22,
"capInsetsHeight": 1,
"capInsetsWidth": 1,
"capInsetsX": 0,
"capInsetsY": 0,
"fileName": null,
"fileNameData": {
"path": "imgres/main/b_bk.png",
"plistFile": "",
"resourceType": 0
},
"scale9Enable": false,
"scale9Height": 30,
"scale9Width": 150
}
}
],
"options": {
"__type": "PanelSurrogate:#EditorCommon.JsonModel.Component.GUI",
"classname": "Panel",
"name": "Panel_top",
"ZOrder": 0,
"actiontag": 48653720,
"anchorPointX": 0,
"anchorPointY": 0,
"classType": "CocoStudio.EngineAdapterWrap.CSPanel",
"colorB": 255,
"colorG": 255,
"colorR": 255,
"customProperty": "",
"flipX": false,
"flipY": false,
"height": 50,
"ignoreSize": false,
"layoutParameter": null,
"opacity": 255,
"positionPercentX": 0.2973684,
"positionPercentY": 0,
"positionType": 0,
"rotation": 0,
"scaleX": 1,
"scaleY": 1,
"sizePercentX": 0.7017544,
"sizePercentY": 1,
"sizeType": 0,
"tag": 110,
"touchAble": true,
"useMergedTexture": false,
"visible": true,
"width": 800,
"x": 339,
"y": 0,
"adaptScreen": false,
"backGroundImage": null,
"backGroundImageData": null,
"backGroundScale9Enable": false,
"bgColorB": 255,
"bgColorG": 200,
"bgColorOpacity": 0,
"bgColorR": 150,
"bgEndColorB": 255,
"bgEndColorG": 200,
"bgEndColorR": 150,
"bgStartColorB": 255,
"bgStartColorG": 255,
"bgStartColorR": 255,
"capInsetsHeight": 1,
"capInsetsWidth": 1,
"capInsetsX": 0,
"capInsetsY": 0,
"clipAble": false,
"colorType": 1,
"layoutType": 0,
"vectorX": 0,
"vectorY": -0.5
}
}
],
"options": {
"__type": "PanelSurrogate:#EditorCommon.JsonModel.Component.GUI",
"classname": "Panel",
"name": "Panel_40",
"ZOrder": 0,
"actiontag": -1,
"anchorPointX": 0,
"anchorPointY": 0,
"classType": "CocoStudio.EngineAdapterWrap.CSPanel",
"colorB": 255,
"colorG": 255,
"colorR": 255,
"customProperty": "",
"flipX": false,
"flipY": false,
"height": 50,
"ignoreSize": false,
"layoutParameter": null,
"opacity": 255,
"positionPercentX": 0,
"positionPercentY": 0,
"positionType": 0,
"rotation": 0,
"scaleX": 1,
"scaleY": 1,
"sizePercentX": 1,
"sizePercentY": 1,
"sizeType": 0,
"tag": 109,
"touchAble": true,
"useMergedTexture": false,
"visible": true,
"width": 1140,
"x": 0,
"y": 0,
"adaptScreen": false,
"backGroundImage": null,
"backGroundImageData": null,
"backGroundScale9Enable": false,
"bgColorB": 255,
"bgColorG": 200,
"bgColorOpacity": 0,
"bgColorR": 150,
"bgEndColorB": 255,
"bgEndColorG": 200,
"bgEndColorR": 150,
"bgStartColorB": 255,
"bgStartColorG": 255,
"bgStartColorR": 255,
"capInsetsHeight": 1,
"capInsetsWidth": 1,
"capInsetsX": 0,
"capInsetsY": 0,
"clipAble": false,
"colorType": 1,
"layoutType": 0,
"vectorX": 0,
"vectorY": -0.5
}
}
}
